{
    "class": "DepictionTabView",
    "headerImage": "https://dcsyhi1998.github.io/Banners/ZetsuBaner.png",
    "minVersion": "0.3",
    "tabs": [
      {
        "class": "DepictionStackView",
        "tabname": "Details",
        "tintColor": "#c1c1c2",
        "views": [
            {
                "class": "DepictionSubheaderView",
                "title": "Description",
                "useBoldText": true,
                "useBottomMargin": false
            },
            {
                "class": "DepictionMarkdownView",
                "markdown":"<p>Zetsu is a Tweak that allows the app to Multitask.How to start: Select Zetsu from 3D Touch shortcuts for the app you want to multitask.</p>",
                "useRawFormat": true
            },
            {
                "class": "DepictionSubheaderView",
                "title": "License",
                "useBoldText": true,
                "useBottomMargin": false
            },
            {
                "class": "DepictionMarkdownView",
                "markdown":"<p>Zetsu was made using the source of <a href=\"https://github.com/nicho1asdev/Konban\">konban13</a>. Without this source, Zetsu would have been difficult to implement.I am very grateful to the developers Eva (Nepeta) and nicho1asdev.<br><br>Click here to check the <a href=\"https://github.com/nicho1asdev/Konban/blob/master/LICENSE\">License</a></p>",
                "useRawFormat": true
            },
            {
                "class": "DepictionSeparatorView"
            },
            {
                "class": "DepictionSubheaderView",
                "title": "Screenshots",
                "useBoldText": true,
                "useBottomMargin": false
            },
            {
                "class": "DepictionScreenshotsView",
                "itemCornerRadius": 8,
                "itemSize": "{360, 250}",
                "screenshots": [
                {
                    "accessibilityText": "Screenshot",
                    "url": "https://dcsyhi1998.github.io/icons/Airaw/demo.png"
                },
                {
                    "accessibilityText": "Screenshot",
                    "url": "https://dcsyhi1998.github.io/icons/Airaw/demo1.png"
                },
                {
                    "accessibilityText": "Screenshot",
                    "url": "https://dcsyhi1998.github.io/icons/Airaw/demo2.png"
                },
                {
                    "accessibilityText": "Screenshot",
                    "url": "https://dcsyhi1998.github.io/icons/Airaw/demo3.png"
                },
                {
                    "accessibilityText": "Screenshot",
                    "url": "https://dcsyhi1998.github.io/icons/Airaw/demo4.png"
                }
                ]
            },
            {
                "class": "DepictionSpacerView",
                "spacing": 16
            },
            {
                "class": "DepictionSeparatorView"
            },
            {
                "class": "DepictionSpacerView",
                "spacing": 16
            },
            {
                "class": "DepictionHeaderView",
                "title": "Information",
                "useBoldText": true,
                "useBottomMargin": false
            },
            {
                "class": "DepictionSpacerView",
                "spacing": 8
            },
            {
                "class": "DepictionTableTextView",
                "text": "Dcsyhi (@linux_n1)",
                "title": "Author"
            },
            {
                "class": "DepictionTableTextView",
                "text": "1.0",
                "title": "Version"
            },
            {
                "class": "DepictionTableTextView",
                "text": "iOS13.0 - 15.x",
                "title": "Compatibility"
            },
            {
                "class": "DepictionTableTextView",
                "text": "Rocketbootstrapm,PreferenceLoader",
                "title": "Dependency"
            },
            {
                "class": "DepictionSpacerView",
                "spacing": 16
            },
            {
                "class": "DepictionSeparatorView"
            },
            {
                "class": "DepictionSpacerView",
                "spacing": 16
            },
            {
                "action": "https://twitter.com/intent/follow?screen_name=linux_n1",
                "class": "DepictionTableButtonView",
                "title": "Find me on Twitter (@linux_n1)",
                "openExternal": true
            },
            {
                "action": "mailto:dcsyhi1998@gmail.com",
                "class": "DepictionTableButtonView",
                "title": "Send me an email"
            },
            {
                "action": "https://www.paypal.me/DevDcsyhi",
                "class": "DepictionTableButtonView",
                "title": "Buy me a 🍺 via PayPal"
            },
            {
                "class": "DepictionSpacerView",
                "spacing": 40
            },
            {
                "URL": "https://dcsyhi1998.github.io/CydiaIcon.png",
                "alignment": 1,
                "class": "DepictionImageView",
                "cornerRadius": 0,
                "height": 45,
                "width": 45
            },
            {
                "class": "DepictionSpacerView",
                "spacing": 16
            },
            {
                "class": "DepictionReviewView",
                "title": "Amazing tweak",
                "author": "M2",
                "markdown":"Best Multitasking Tweak.",
                "rating": 5
            },
            {
                "class": "DepictionReviewView",
                "title": "Best",
                "author": "ㄇㄉㄈㄎ",
                "markdown":"Zetsu, the best multitasking tweak.",
                "rating": 5
            }
        ]
      },
      {
        "class": "DepictionStackView",
        "tabname": "Changelog",
        "tintColor": "#c1c1c2",
        "views": [
          {
            "class": "DepictionSubheaderView",
            "title": "1.0",
            "useBoldText": true,
            "useBottomMargin": false
          },
          {
            "class": "DepictionMarkdownView",
            "markdown": "<ul>\n<li>Initial Release (iOS15 Support)</li>\n</ul>",
            "useRawFormat": true
          }
        ]
      }
    ],
    "tintColor": "#c1c1c2"
  }